README.md
setup.cfg
setup.py
test/test.py
wintoast/__init__.py
wintoast/__main__.py
wintoast.egg-info/PKG-INFO
wintoast.egg-info/SOURCES.txt
wintoast.egg-info/dependency_links.txt
wintoast.egg-info/requires.txt
wintoast.egg-info/top_level.txt