Metadata-Version: 2.1
Name: wintoast
Version: 0.2
Summary: An easy-to-use Python library for displaying Windows 10 Toast Notifications
Home-page: https://github.com/samkenhuang/Windows-Toast-Notifications
Author: Jithu R Jacob
Author-email: =samkenhuang@gmail.com
License: BSD
Download-URL: https://github.com/samkenhuang/Windows-Toast-Notifications/0.2
Platform: UNKNOWN
Classifier: Development Status :: 3 - Alpha
Classifier: Topic :: Utilities
Classifier: Operating System :: Microsoft
Classifier: Environment :: Win32 (MS Windows)
Classifier: License :: OSI Approved :: MIT License
